odoo/addons/quality_control_mrp/README.rst
odoo/addons/quality_control_mrp/__init__.py
odoo/addons/quality_control_mrp/__manifest__.py
odoo/addons/quality_control_mrp/data/quality_control_mrp_data.xml
odoo/addons/quality_control_mrp/i18n/ca.po
odoo/addons/quality_control_mrp/i18n/de.po
odoo/addons/quality_control_mrp/i18n/el_GR.po
odoo/addons/quality_control_mrp/i18n/es.po
odoo/addons/quality_control_mrp/i18n/es_ES.po
odoo/addons/quality_control_mrp/i18n/es_MX.po
odoo/addons/quality_control_mrp/i18n/eu.po
odoo/addons/quality_control_mrp/i18n/fi.po
odoo/addons/quality_control_mrp/i18n/fr.po
odoo/addons/quality_control_mrp/i18n/fr_CH.po
odoo/addons/quality_control_mrp/i18n/fr_FR.po
odoo/addons/quality_control_mrp/i18n/gl.po
odoo/addons/quality_control_mrp/i18n/hr.po
odoo/addons/quality_control_mrp/i18n/hr_HR.po
odoo/addons/quality_control_mrp/i18n/it.po
odoo/addons/quality_control_mrp/i18n/nl.po
odoo/addons/quality_control_mrp/i18n/nl_NL.po
odoo/addons/quality_control_mrp/i18n/pt.po
odoo/addons/quality_control_mrp/i18n/pt_BR.po
odoo/addons/quality_control_mrp/i18n/quality_control_mrp.pot
odoo/addons/quality_control_mrp/i18n/ro.po
odoo/addons/quality_control_mrp/i18n/ru.po
odoo/addons/quality_control_mrp/i18n/sk.po
odoo/addons/quality_control_mrp/i18n/sl.po
odoo/addons/quality_control_mrp/i18n/tr.po
odoo/addons/quality_control_mrp/i18n/tr_TR.po
odoo/addons/quality_control_mrp/i18n/vi_VN.po
odoo/addons/quality_control_mrp/i18n/zh_CN.po
odoo/addons/quality_control_mrp/migrations/12.0.1.0.0/pre-migration.py
odoo/addons/quality_control_mrp/models/__init__.py
odoo/addons/quality_control_mrp/models/mrp_production.py
odoo/addons/quality_control_mrp/models/qc_inspection.py
odoo/addons/quality_control_mrp/readme/CONTRIBUTORS.rst
odoo/addons/quality_control_mrp/readme/DESCRIPTION.rst
odoo/addons/quality_control_mrp/static/description/icon.png
odoo/addons/quality_control_mrp/static/description/index.html
odoo/addons/quality_control_mrp/tests/__init__.py
odoo12_addon_quality_control_mrp-12.0.1.0.1.dist-info/METADATA
odoo12_addon_quality_control_mrp-12.0.1.0.1.dist-info/WHEEL
odoo12_addon_quality_control_mrp-12.0.1.0.1.dist-info/top_level.txt
odoo12_addon_quality_control_mrp-12.0.1.0.1.dist-info/RECORD
