Metadata-Version: 2.1
Name: odoo12-addon-quality-control-mrp
Version: 12.0.1.0.1
Summary: MRP extension for quality control
Home-page: https://github.com/OCA/manufacturequality_control_mrp
Author: OdooMRP team, AvanzOSC, Serv. Tecnol. Avanzados - Pedro M. Baeza, Agile Business Group, Odoo Community Association (OCA)
Author-email: support@odoo-community.org
License: AGPL-3
Platform: UNKNOWN
Classifier: Programming Language :: Python
Classifier: Framework :: Odoo
Classifier: Framework :: Odoo :: 12.0
Classifier: License :: OSI Approved :: GNU Affero General Public License v3
Requires-Python: >=3.5
Requires-Dist: odoo12-addon-quality-control-stock
Requires-Dist: odoo (<12.1dev,>=12.0a)
